Metadata-Version: 2.1
Name: spaceprob
Version: 0.0.3
Summary: Live stats for Voyager 1 space prob
Home-page: UNKNOWN
Author: Sumit Bathla
Author-email: sumitbathla01@gmail.com
License: MIT
Keywords: voyager1
Platform: UNKNOWN
Classifier: Development Status :: 5 - Production/Stable
Classifier: Intended Audience :: Education
Classifier: Operating System :: Microsoft :: Windows :: Windows 10
Classifier: License :: OSI Approved :: MIT License
Classifier: Programming Language :: Python :: 3
License-File: LICENSE.txt
